Metadata-Version: 2.1
Name: gtbump
Version: 0.2.0
Summary: git-tag-bump: a simple utility for quickly bumping Git semver tags
Home-page: https://github.com/knadh/gtbump
Author: Kailash Nadh
Author-email: kailash@nadh.in
License: MIT License
Download-URL: https://github.com/knadh/gtbump
Platform: UNKNOWN
Classifier: Topic :: Software Development :: Version Control
Classifier: Topic :: Software Development :: Version Control :: Git
Classifier: Topic :: Software Development :: Build Tools
